azure/core/experimental/__init__.py
azure/core/experimental/_version.py
azure/core/experimental/py.typed
azure/core/experimental/transport/__init__.py
azure/core/experimental/transport/_httpx.py
azure/core/experimental/transport/_httpx_async.py
azure/core/experimental/transport/_pyodide.py
azure_core_experimental-1.0.0b4.dist-info/LICENSE
azure_core_experimental-1.0.0b4.dist-info/METADATA
azure_core_experimental-1.0.0b4.dist-info/WHEEL
azure_core_experimental-1.0.0b4.dist-info/top_level.txt
azure_core_experimental-1.0.0b4.dist-info/RECORD
