Metadata-Version: 2.1
Name: azure-core-experimental
Version: 1.0.0b4
Summary: Microsoft Azure Core Experimental Library for Python
Home-page: https://github.com/Azure/azure-sdk-for-python/tree/main/sdk/core/azure-core-experimental
Author: Microsoft Corporation
Author-email: azpysdkhelp@microsoft.com
License: MIT License
Classifier: Development Status :: 4 - Beta
Classifier: Programming Language :: Python
Classifier: Programming Language :: Python :: 3 :: Only
Classifier: Programming Language :: Python :: 3
Classifier: Programming Language :: Python :: 3.7
Classifier: Programming Language :: Python :: 3.8
Classifier: Programming Language :: Python :: 3.9
Classifier: Programming Language :: Python :: 3.10
Classifier: Programming Language :: Python :: 3.11
Classifier: License :: OSI Approved :: MIT License
Requires-Python: >=3.7
License-File: LICENSE
Requires-Dist: azure-core <2.0.0,>=1.25.0
